libopy/__init__.py
libopy/_transaction.py
libopy/_wallet.py
libopy/typing.py
tests/__init__.py
tests/test_transaction.py
tests/test_wallet.py
libopy-1.0.0.dist-info/LICENSE
libopy-1.0.0.dist-info/METADATA
libopy-1.0.0.dist-info/WHEEL
libopy-1.0.0.dist-info/top_level.txt
libopy-1.0.0.dist-info/RECORD
