Metadata-Version: 2.1
Name: libopy
Version: 1.0.0
Summary: Package for transaction offline transaction signing
Home-page: https://github.com/evdatsion/libopy
Author: @evdatsion
Author-email: sarmad@magnusmage.com
License: UNKNOWN
Platform: UNKNOWN
Classifier: Programming Language :: Python :: 3
Classifier: License :: OSI Approved :: MIT License
Classifier: Operating System :: OS Independent
Requires-Python: >=3.6
